MANIFEST.in
README.txt
setup.py
docs/HISTORY.txt
src/zeam/__init__.py
src/zeam.form.composed.egg-info/PKG-INFO
src/zeam.form.composed.egg-info/SOURCES.txt
src/zeam.form.composed.egg-info/dependency_links.txt
src/zeam.form.composed.egg-info/namespace_packages.txt
src/zeam.form.composed.egg-info/not-zip-safe
src/zeam.form.composed.egg-info/requires.txt
src/zeam.form.composed.egg-info/top_level.txt
src/zeam/form/__init__.py
src/zeam/form/composed/__init__.py
src/zeam/form/composed/configure.zcml
src/zeam/form/composed/form.py
src/zeam/form/composed/ftesting.zcml
src/zeam/form/composed/interfaces.py
src/zeam/form/composed/meta.py
src/zeam/form/composed/testing.py
src/zeam/form/composed/default_templates/composedformtemplate.cpt
src/zeam/form/composed/default_templates/subformgrouptemplate.cpt
src/zeam/form/composed/default_templates/subformtemplate.cpt
src/zeam/form/composed/ftests/__init__.py
src/zeam/form/composed/ftests/test_form.py
src/zeam/form/composed/ftests/forms/__init__.py
src/zeam/form/composed/ftests/forms/composed.py
src/zeam/form/composed/ftests/forms/explicitorder.py
src/zeam/form/composed/ftests/forms/group.py
src/zeam/form/composed/ftests/forms/implicitorder.py
src/zeam/form/composed/tests/__init__.py
src/zeam/form/composed/tests/forms.txt
src/zeam/form/composed/tests/test_doctest.py