Metadata-Version: 1.0
Name: zeam.form.composed
Version: 1.3
Summary: Composed form support for zeam.form
Home-page: http://pypi.python.org/pypi/zeam.form.composed
Author: Sylvain Viollon
Author-email: thefunny@gmail.com
License: BSD
Keywords: zeam form composed
Platform: UNKNOWN
Classifier: Programming Language :: Python
Classifier: Topic :: Software Development :: Libraries :: Python Modules
